trivialai/bedrock.py
trivialai/bistream.py
trivialai/bistream_types.py
trivialai/chatgpt.py
trivialai/claude.py
trivialai/filesystem.py
trivialai/gcp.py
trivialai/json_shaped.py
trivialai/jsonesque.py
trivialai/llm.py
trivialai/log.py
trivialai/ollama.py
trivialai/util.py
trivialai/agent/core.py
trivialai/agent/prompting.py
trivialai/agent/toolbox.py
trivialai/agent/toolkit.py
trivialai/embedding/core.py
trivialai/vectorstore/base.py
trivialai/vectorstore/chromadb.py
trivialai/vectorstore/core.py
trivialai-0.5.26.dist-info/licenses/LICENSE.txt
trivialai-0.5.26.dist-info/METADATA
trivialai-0.5.26.dist-info/WHEEL
trivialai-0.5.26.dist-info/top_level.txt
trivialai-0.5.26.dist-info/RECORD
