Metadata-Version: 2.4
Name: trivialai
Version: 0.5.26
Summary: A trivial set of API bindings for AI models, because I'd like them to be easy to use.
Author-email: inaimathi <leo.zovic@gmail.com>
Project-URL: Homepage, https://github.com/inaimathi/trivialai
Project-URL: Issues, https://github.com/inaimathi/trivialai/issues
Classifier: Programming Language :: Python :: 3
Classifier: License :: OSI Approved :: MIT License
Classifier: Operating System :: OS Independent
Requires-Python: >=3.10
License-File: LICENSE.txt
Requires-Dist: httpx~=0.27
Requires-Dist: tenacity<10,>=9.1
Requires-Dist: json5
Requires-Dist: chromadb==1.0.15
Provides-Extra: http2
Requires-Dist: httpx[http2]~=0.27; extra == "http2"
Provides-Extra: bedrock
Requires-Dist: boto3==1.40.76; extra == "bedrock"
Provides-Extra: gcp
Requires-Dist: google-auth<3,>=2.31; extra == "gcp"
Requires-Dist: vertexai==1.49.0; extra == "gcp"
Provides-Extra: all
Requires-Dist: httpx[http2]~=0.27; extra == "all"
Requires-Dist: boto3==1.40.76; extra == "all"
Requires-Dist: google-auth<3,>=2.31; extra == "all"
Requires-Dist: vertexai==1.49.0; extra == "all"
Dynamic: license-file
